anemoi/transform/__init__.py
anemoi/transform/__main__.py
anemoi/transform/_version.py
anemoi/transform/constants.py
anemoi/transform/documentation.py
anemoi/transform/fields.py
anemoi/transform/filter.py
anemoi/transform/flavour.py
anemoi/transform/source.py
anemoi/transform/transform.py
anemoi/transform/workflow.py
anemoi/transform/commands/__init__.py
anemoi/transform/commands/filters.py
anemoi/transform/commands/get-grid.py
anemoi/transform/commands/make-regrid-matrix.py
anemoi/transform/data/__init__.py
anemoi/transform/filters/__init__.py
anemoi/transform/filters/accum_to_interval.py
anemoi/transform/filters/apply_mask.py
anemoi/transform/filters/clear_step.py
anemoi/transform/filters/clipper.py
anemoi/transform/filters/cos_sin_from_rad.py
anemoi/transform/filters/cos_sin_mean_wave_direction.py
anemoi/transform/filters/dewpoint.py
anemoi/transform/filters/empty.py
anemoi/transform/filters/glacier_mask.py
anemoi/transform/filters/icon_refinement_level.py
anemoi/transform/filters/lambda_filters.py
anemoi/transform/filters/land_parameters.py
anemoi/transform/filters/lnsp_to_sp.py
anemoi/transform/filters/matching.py
anemoi/transform/filters/noop.py
anemoi/transform/filters/oras6_clipping.py
anemoi/transform/filters/orog_to_z.py
anemoi/transform/filters/q_height.py
anemoi/transform/filters/q_to_r.py
anemoi/transform/filters/regrid.py
anemoi/transform/filters/remove_nans.py
anemoi/transform/filters/rename.py
anemoi/transform/filters/repeat_members.py
anemoi/transform/filters/rescale.py
anemoi/transform/filters/rodeo_opera_clipping.py
anemoi/transform/filters/rodeo_opera_preprocessing.py
anemoi/transform/filters/rotate_winds.py
anemoi/transform/filters/snow_cover.py
anemoi/transform/filters/sum.py
anemoi/transform/filters/timeseries.py
anemoi/transform/filters/uv_to_ddff.py
anemoi/transform/filters/w_to_wz.py
anemoi/transform/grids/__init__.py
anemoi/transform/grids/icon.py
anemoi/transform/grids/unstructured.py
anemoi/transform/grouping/__init__.py
anemoi_transform-0.1.20.dist-info/licenses/LICENSE
anemoi_transform-0.1.20.dist-info/METADATA
anemoi_transform-0.1.20.dist-info/WHEEL
anemoi_transform-0.1.20.dist-info/entry_points.txt
anemoi_transform-0.1.20.dist-info/top_level.txt
anemoi_transform-0.1.20.dist-info/RECORD
