Metadata-Version: 2.4
Name: anemoi-transform
Version: 0.1.20
Summary: A package to hold various data transformation functions to support training of ML models on ECMWF data.
Author-email: "European Centre for Medium-Range Weather Forecasts (ECMWF)" <software.support@ecmwf.int>
License:                                  Apache License
Project-URL: Documentation, https://anemoi-transform.readthedocs.io/
Project-URL: Homepage, https://github.com/ecmwf/anemoi-transform/
Project-URL: Issues, https://github.com/ecmwf/anemoi-transform/issues
Project-URL: Repository, https://github.com/ecmwf/anemoi-transform/
Keywords: ai,tools
Classifier: Development Status :: 4 - Beta
Classifier: Intended Audience :: Developers
Classifier: License :: OSI Approved :: Apache Software License
Classifier: Operating System :: OS Independent
Classifier: Programming Language :: Python :: 3 :: Only
Classifier: Programming Language :: Python :: 3.10
Classifier: Programming Language :: Python :: 3.11
Classifier: Programming Language :: Python :: 3.12
Classifier: Programming Language :: Python :: Implementation :: CPython
Classifier: Programming Language :: Python :: Implementation :: PyPy
Requires-Python: >=3.10
License-File: LICENSE
Requires-Dist: anemoi-utils>=0.4.36
Requires-Dist: cfunits
Requires-Dist: earthkit-data>=0.12.4
Requires-Dist: earthkit-geo>=0.3
Requires-Dist: earthkit-meteo>=0.4.1
Requires-Dist: earthkit-regrid>=0.4
Provides-Extra: all
Requires-Dist: anemoi-transform; extra == "all"
Provides-Extra: dev
Requires-Dist: anemoi-transform[all,docs,tests]; extra == "dev"
Provides-Extra: docs
Requires-Dist: nbsphinx; extra == "docs"
Requires-Dist: numpydoc; extra == "docs"
Requires-Dist: pandoc; extra == "docs"
Requires-Dist: requests; extra == "docs"
Requires-Dist: ruamel-yaml; extra == "docs"
Requires-Dist: sphinx>=8.2; python_version >= "3.11" and extra == "docs"
Requires-Dist: sphinx-argparse<0.5; extra == "docs"
Requires-Dist: sphinx-rtd-theme; extra == "docs"
Requires-Dist: termcolor; extra == "docs"
Provides-Extra: tests
Requires-Dist: pytest; extra == "tests"
Dynamic: license-file
